ipyfernel/__init__.py
ipyfernel/_modidx.py
ipyfernel/core.py
ipyfernel-0.0.5.dist-info/licenses/LICENSE
ipyfernel-0.0.5.dist-info/METADATA
ipyfernel-0.0.5.dist-info/WHEEL
ipyfernel-0.0.5.dist-info/entry_points.txt
ipyfernel-0.0.5.dist-info/top_level.txt
ipyfernel-0.0.5.dist-info/RECORD
